LICENSE.txt
MANIFEST.in
README.org
dumpling.py
setup.cfg
setup.py
test_dumpling.py
dumpling.egg-info/PKG-INFO
dumpling.egg-info/SOURCES.txt
dumpling.egg-info/dependency_links.txt
dumpling.egg-info/requires.txt
dumpling.egg-info/top_level.txt