Metadata-Version: 1.1
Name: dumpling
Version: 0.1.3
Summary: DUMPLING: command-line app controller
Home-page: http://github.com/rnaer/dumpling
Author: Zhenjiang Zech Xu
Author-email: zhenjiang.xu@gmail.com
License: BSD
Keywords: application wrapper
Platform: UNKNOWN
Classifier: Development Status :: 4 - Beta
Classifier: License :: OSI Approved :: BSD License
Classifier: Environment :: Console
Classifier: Topic :: Software Development :: Libraries
Classifier: Programming Language :: Python
Classifier: Programming Language :: Python :: 3
Classifier: Programming Language :: Python :: 3.4
Classifier: Programming Language :: Python :: 3.5
Classifier: Operating System :: Unix
Classifier: Operating System :: POSIX
Classifier: Operating System :: Microsoft
Classifier: Operating System :: MacOS :: MacOS X
